sqs_py/__init__.py
sqs_py/_base.py
sqs_py/about.py
sqs_py/consumer.py
sqs_py/producer.py
sqs_py-1.0.0.dist-info/METADATA
sqs_py-1.0.0.dist-info/WHEEL
sqs_py-1.0.0.dist-info/top_level.txt
sqs_py-1.0.0.dist-info/RECORD
