Metadata-Version: 2.1
Name: sqs-py
Version: 1.0.0
Summary: AWS SQS utility package for producing and consuming messages
Home-page: https://github.com/wengjiyao/sqs_py
Author: wengjiyao
Author-email: w.j@live.ca
License: MIT
Keywords: aws sqs messages producer/consumer
Platform: UNKNOWN
Classifier: Development Status :: 4 - Beta
Classifier: Intended Audience :: Developers
Classifier: Topic :: Software Development :: Libraries
Classifier: License :: OSI Approved :: MIT License
Classifier: Programming Language :: Python :: 3.7
Requires-Dist: boto3
